qt_await/__init__.py
qt_await/core.py
qt_await/utils.py
qt_await-0.1.dist-info/LICENSE
qt_await-0.1.dist-info/WHEEL
qt_await-0.1.dist-info/METADATA
qt_await-0.1.dist-info/RECORD
