Metadata-Version: 2.3
Name: qt_await
Version: 0.1
Summary: Use 'await' syntax with Qt signals
Author-email: Thomas Kluyver <thomas@kluyver.me.uk>
Classifier: License :: OSI Approved :: MIT License
Requires-Dist: qtpy
Requires-Dist: pytest ; extra == "test"
Requires-Dist: pytest-qt ; extra == "test"
Project-URL: Home, https://github.com/takluyver/qt_await
Provides-Extra: test
